xgroovy/__init__.py
xgroovy/downloader.py
xgroovy/main.py
xgroovy/scraper.py
xgroovy-0.1.4.dist-info/LICENCE.txt
xgroovy-0.1.4.dist-info/METADATA
xgroovy-0.1.4.dist-info/WHEEL
xgroovy-0.1.4.dist-info/entry_points.txt
xgroovy-0.1.4.dist-info/top_level.txt
xgroovy-0.1.4.dist-info/RECORD
