Metadata-Version: 2.1
Name: xgroovy
Version: 0.1.4
Summary: An asynchronous web scraper and video downloader using pyppeteer
Home-page: https://github.com/codex-ML/xgroovy
Author: codex-ML
Classifier: Programming Language :: Python :: 3
Classifier: License :: OSI Approved :: MIT License
Classifier: Operating System :: OS Independent
Requires-Python: >=3.6
License-File: LICENCE.txt
Requires-Dist: pyppeteer
Requires-Dist: asyncio
Requires-Dist: wheel
Requires-Dist: loguru
